snncompare/Experiment_runner.py
snncompare/__init__.py
snncompare/__main__.py
snncompare/helper.py
snncompare/old_conversion.py
snncompare/verification_generic.py
snncompare/arg_parser/__init__.py
snncompare/arg_parser/arg_parser.py
snncompare/arg_parser/arg_verification.py
snncompare/exp_setts/Supported_experiment_settings.py
snncompare/exp_setts/__init__.py
snncompare/exp_setts/verify_experiment_settings.py
snncompare/exp_setts/adapt/Adaptation_Rad_settings.py
snncompare/exp_setts/adapt/__init__.py
snncompare/exp_setts/algos/DUMMY.py
snncompare/exp_setts/algos/MDSA.py
snncompare/exp_setts/algos/__init__.py
snncompare/exp_setts/algos/algo_helper.py
snncompare/exp_setts/algos/get_alg_configs.py
snncompare/exp_setts/algos/verify_algos.py
snncompare/exp_setts/custom_setts/__init__.py
snncompare/exp_setts/default_setts/__init__.py
snncompare/exp_setts/default_setts/create_default_settings.py
snncompare/exp_setts/rad/__init__.py
snncompare/exp_setts/rad/permanent_neuron_death.py
snncompare/exp_setts/rad/radiation.py
snncompare/exp_setts/run_config/Supported_run_settings.py
snncompare/exp_setts/run_config/__init__.py
snncompare/exp_setts/run_config/verify_run_completion.py
snncompare/exp_setts/run_config/verify_run_settings.py
snncompare/export_results/Output.py
snncompare/export_results/Output_stage_12.py
snncompare/export_results/Output_stage_34.py
snncompare/export_results/Plot_to_tex.py
snncompare/export_results/__init__.py
snncompare/export_results/check_json_graphs.py
snncompare/export_results/check_nx_graphs.py
snncompare/export_results/export_json_results.py
snncompare/export_results/export_nx_graph_to_json.py
snncompare/export_results/helper.py
snncompare/export_results/load_json_to_nx_graph.py
snncompare/export_results/load_pickles_get_results.py
snncompare/export_results/plot_graphs.py
snncompare/export_results/verify_json_graphs.py
snncompare/export_results/verify_nx_graphs.py
snncompare/export_results/verify_stage_1_graphs.py
snncompare-0.0.7.dist-info/METADATA
snncompare-0.0.7.dist-info/WHEEL
snncompare-0.0.7.dist-info/entry_points.txt
snncompare-0.0.7.dist-info/licence
snncompare-0.0.7.dist-info/top_level.txt
snncompare-0.0.7.dist-info/RECORD
