Metadata-Version: 2.1
Name: snncompare
Version: 0.0.7
Summary: compares snn algorithms against neumann algorithms
Home-page: https://github.com/a-t-0/snncompare
Author: a-t-0
Author-email: no-email@no-email.org
Maintainer: a-t-0
Maintainer-email: no-email@no-email.org
License: AGPLv3
Classifier: Development Status :: 2 - Pre-Alpha
Classifier: Environment :: Console
Classifier: Intended Audience :: Science/Research
Classifier: License :: OSI Approved :: GNU Affero General Public License v3
Classifier: Programming Language :: Python
Classifier: Programming Language :: Python :: 3
Classifier: Programming Language :: Python :: 3 :: Only
Classifier: Programming Language :: Python :: 3.10
Classifier: Topic :: Scientific/Engineering :: Artificial Intelligence
Requires-Python: >=3.10
License-File: licence
Requires-Dist: jsons (>=1.6.3)
Requires-Dist: matplotlib (>=3.6.1)
Requires-Dist: networkx (>=2.8.7)
Requires-Dist: numpy (>=1.23.4)
Requires-Dist: pytest-cov (>=4.0.0)
